<?xml version="1.0" encoding="utf-8"?>
<ArrayOfNapiAdagPerEtkezesFajta xmlns:xsi="http://www.w3.org/2001/XMLSchema-instance" xmlns:xsd="http://www.w3.org/2001/XMLSchema">
  <NapiAdagPerEtkezesFajta>
    <Datum>2022-07-04</Datum>
    <EtkezesFajta>N</EtkezesFajta>
    <Adag>2745</Adag>
  </NapiAdagPerEtkezesFajta>
  <NapiAdagPerEtkezesFajta>
    <Datum>2022-07-04</Datum>
    <EtkezesFajta>D</EtkezesFajta>
    <Adag>17</Adag>
  </NapiAdagPerEtkezesFajta>
  <NapiAdagPerEtkezesFajta>
    <Datum>2022-07-05</Datum>
    <EtkezesFajta>N</EtkezesFajta>
    <Adag>2762</Adag>
  </NapiAdagPerEtkezesFajta>
  <NapiAdagPerEtkezesFajta>
    <Datum>2022-07-05</Datum>
    <EtkezesFajta>D</EtkezesFajta>
    <Adag>17</Adag>
  </NapiAdagPerEtkezesFajta>
  <NapiAdagPerEtkezesFajta>
    <Datum>2022-07-06</Datum>
    <EtkezesFajta>N</EtkezesFajta>
    <Adag>2749</Adag>
  </NapiAdagPerEtkezesFajta>
  <NapiAdagPerEtkezesFajta>
    <Datum>2022-07-06</Datum>
    <EtkezesFajta>D</EtkezesFajta>
    <Adag>17</Adag>
  </NapiAdagPerEtkezesFajta>
  <NapiAdagPerEtkezesFajta>
    <Datum>2022-07-07</Datum>
    <EtkezesFajta>N</EtkezesFajta>
    <Adag>2747</Adag>
  </NapiAdagPerEtkezesFajta>
  <NapiAdagPerEtkezesFajta>
    <Datum>2022-07-07</Datum>
    <EtkezesFajta>D</EtkezesFajta>
    <Adag>17</Adag>
  </NapiAdagPerEtkezesFajta>
  <NapiAdagPerEtkezesFajta>
    <Datum>2022-07-08</Datum>
    <EtkezesFajta>N</EtkezesFajta>
    <Adag>2697</Adag>
  </NapiAdagPerEtkezesFajta>
  <NapiAdagPerEtkezesFajta>
    <Datum>2022-07-08</Datum>
    <EtkezesFajta>D</EtkezesFajta>
    <Adag>17</Adag>
  </NapiAdagPerEtkezesFajta>
  <NapiAdagPerEtkezesFajta>
    <Datum>2022-07-11</Datum>
    <EtkezesFajta>N</EtkezesFajta>
    <Adag>2403</Adag>
  </NapiAdagPerEtkezesFajta>
  <NapiAdagPerEtkezesFajta>
    <Datum>2022-07-11</Datum>
    <EtkezesFajta>D</EtkezesFajta>
    <Adag>9</Adag>
  </NapiAdagPerEtkezesFajta>
  <NapiAdagPerEtkezesFajta>
    <Datum>2022-07-12</Datum>
    <EtkezesFajta>N</EtkezesFajta>
    <Adag>2404</Adag>
  </NapiAdagPerEtkezesFajta>
  <NapiAdagPerEtkezesFajta>
    <Datum>2022-07-12</Datum>
    <EtkezesFajta>D</EtkezesFajta>
    <Adag>9</Adag>
  </NapiAdagPerEtkezesFajta>
  <NapiAdagPerEtkezesFajta>
    <Datum>2022-07-13</Datum>
    <EtkezesFajta>N</EtkezesFajta>
    <Adag>2408</Adag>
  </NapiAdagPerEtkezesFajta>
  <NapiAdagPerEtkezesFajta>
    <Datum>2022-07-13</Datum>
    <EtkezesFajta>D</EtkezesFajta>
    <Adag>9</Adag>
  </NapiAdagPerEtkezesFajta>
  <NapiAdagPerEtkezesFajta>
    <Datum>2022-07-14</Datum>
    <EtkezesFajta>N</EtkezesFajta>
    <Adag>2404</Adag>
  </NapiAdagPerEtkezesFajta>
  <NapiAdagPerEtkezesFajta>
    <Datum>2022-07-14</Datum>
    <EtkezesFajta>D</EtkezesFajta>
    <Adag>9</Adag>
  </NapiAdagPerEtkezesFajta>
  <NapiAdagPerEtkezesFajta>
    <Datum>2022-07-15</Datum>
    <EtkezesFajta>N</EtkezesFajta>
    <Adag>2356</Adag>
  </NapiAdagPerEtkezesFajta>
  <NapiAdagPerEtkezesFajta>
    <Datum>2022-07-15</Datum>
    <EtkezesFajta>D</EtkezesFajta>
    <Adag>9</Adag>
  </NapiAdagPerEtkezesFajta>
  <NapiAdagPerEtkezesFajta>
    <Datum>2022-07-18</Datum>
    <EtkezesFajta>N</EtkezesFajta>
    <Adag>2383</Adag>
  </NapiAdagPerEtkezesFajta>
  <NapiAdagPerEtkezesFajta>
    <Datum>2022-07-18</Datum>
    <EtkezesFajta>D</EtkezesFajta>
    <Adag>9</Adag>
  </NapiAdagPerEtkezesFajta>
  <NapiAdagPerEtkezesFajta>
    <Datum>2022-07-19</Datum>
    <EtkezesFajta>N</EtkezesFajta>
    <Adag>2405</Adag>
  </NapiAdagPerEtkezesFajta>
  <NapiAdagPerEtkezesFajta>
    <Datum>2022-07-19</Datum>
    <EtkezesFajta>D</EtkezesFajta>
    <Adag>9</Adag>
  </NapiAdagPerEtkezesFajta>
  <NapiAdagPerEtkezesFajta>
    <Datum>2022-07-20</Datum>
    <EtkezesFajta>N</EtkezesFajta>
    <Adag>2411</Adag>
  </NapiAdagPerEtkezesFajta>
  <NapiAdagPerEtkezesFajta>
    <Datum>2022-07-20</Datum>
    <EtkezesFajta>D</EtkezesFajta>
    <Adag>9</Adag>
  </NapiAdagPerEtkezesFajta>
  <NapiAdagPerEtkezesFajta>
    <Datum>2022-07-21</Datum>
    <EtkezesFajta>N</EtkezesFajta>
    <Adag>2397</Adag>
  </NapiAdagPerEtkezesFajta>
  <NapiAdagPerEtkezesFajta>
    <Datum>2022-07-21</Datum>
    <EtkezesFajta>D</EtkezesFajta>
    <Adag>9</Adag>
  </NapiAdagPerEtkezesFajta>
  <NapiAdagPerEtkezesFajta>
    <Datum>2022-07-22</Datum>
    <EtkezesFajta>N</EtkezesFajta>
    <Adag>2370</Adag>
  </NapiAdagPerEtkezesFajta>
  <NapiAdagPerEtkezesFajta>
    <Datum>2022-07-22</Datum>
    <EtkezesFajta>D</EtkezesFajta>
    <Adag>9</Adag>
  </NapiAdagPerEtkezesFajta>
  <NapiAdagPerEtkezesFajta>
    <Datum>2022-07-25</Datum>
    <EtkezesFajta>N</EtkezesFajta>
    <Adag>2191</Adag>
  </NapiAdagPerEtkezesFajta>
  <NapiAdagPerEtkezesFajta>
    <Datum>2022-07-25</Datum>
    <EtkezesFajta>D</EtkezesFajta>
    <Adag>16</Adag>
  </NapiAdagPerEtkezesFajta>
  <NapiAdagPerEtkezesFajta>
    <Datum>2022-07-26</Datum>
    <EtkezesFajta>N</EtkezesFajta>
    <Adag>2187</Adag>
  </NapiAdagPerEtkezesFajta>
  <NapiAdagPerEtkezesFajta>
    <Datum>2022-07-26</Datum>
    <EtkezesFajta>D</EtkezesFajta>
    <Adag>16</Adag>
  </NapiAdagPerEtkezesFajta>
  <NapiAdagPerEtkezesFajta>
    <Datum>2022-07-27</Datum>
    <EtkezesFajta>N</EtkezesFajta>
    <Adag>2188</Adag>
  </NapiAdagPerEtkezesFajta>
  <NapiAdagPerEtkezesFajta>
    <Datum>2022-07-27</Datum>
    <EtkezesFajta>D</EtkezesFajta>
    <Adag>16</Adag>
  </NapiAdagPerEtkezesFajta>
  <NapiAdagPerEtkezesFajta>
    <Datum>2022-07-28</Datum>
    <EtkezesFajta>N</EtkezesFajta>
    <Adag>2184</Adag>
  </NapiAdagPerEtkezesFajta>
  <NapiAdagPerEtkezesFajta>
    <Datum>2022-07-28</Datum>
    <EtkezesFajta>D</EtkezesFajta>
    <Adag>16</Adag>
  </NapiAdagPerEtkezesFajta>
  <NapiAdagPerEtkezesFajta>
    <Datum>2022-07-29</Datum>
    <EtkezesFajta>N</EtkezesFajta>
    <Adag>2179</Adag>
  </NapiAdagPerEtkezesFajta>
  <NapiAdagPerEtkezesFajta>
    <Datum>2022-07-29</Datum>
    <EtkezesFajta>D</EtkezesFajta>
    <Adag>16</Adag>
  </NapiAdagPerEtkezesFajta>
  <NapiAdagPerEtkezesFajta>
    <Datum>2022-08-01</Datum>
    <EtkezesFajta>N</EtkezesFajta>
    <Adag>2555</Adag>
  </NapiAdagPerEtkezesFajta>
  <NapiAdagPerEtkezesFajta>
    <Datum>2022-08-01</Datum>
    <EtkezesFajta>D</EtkezesFajta>
    <Adag>24</Adag>
  </NapiAdagPerEtkezesFajta>
  <NapiAdagPerEtkezesFajta>
    <Datum>2022-08-02</Datum>
    <EtkezesFajta>D</EtkezesFajta>
    <Adag>24</Adag>
  </NapiAdagPerEtkezesFajta>
  <NapiAdagPerEtkezesFajta>
    <Datum>2022-08-02</Datum>
    <EtkezesFajta>N</EtkezesFajta>
    <Adag>2567</Adag>
  </NapiAdagPerEtkezesFajta>
  <NapiAdagPerEtkezesFajta>
    <Datum>2022-08-03</Datum>
    <EtkezesFajta>D</EtkezesFajta>
    <Adag>24</Adag>
  </NapiAdagPerEtkezesFajta>
  <NapiAdagPerEtkezesFajta>
    <Datum>2022-08-03</Datum>
    <EtkezesFajta>N</EtkezesFajta>
    <Adag>2584</Adag>
  </NapiAdagPerEtkezesFajta>
  <NapiAdagPerEtkezesFajta>
    <Datum>2022-08-04</Datum>
    <EtkezesFajta>N</EtkezesFajta>
    <Adag>2562</Adag>
  </NapiAdagPerEtkezesFajta>
  <NapiAdagPerEtkezesFajta>
    <Datum>2022-08-04</Datum>
    <EtkezesFajta>D</EtkezesFajta>
    <Adag>24</Adag>
  </NapiAdagPerEtkezesFajta>
  <NapiAdagPerEtkezesFajta>
    <Datum>2022-08-05</Datum>
    <EtkezesFajta>D</EtkezesFajta>
    <Adag>24</Adag>
  </NapiAdagPerEtkezesFajta>
  <NapiAdagPerEtkezesFajta>
    <Datum>2022-08-05</Datum>
    <EtkezesFajta>N</EtkezesFajta>
    <Adag>2550</Adag>
  </NapiAdagPerEtkezesFajta>
  <NapiAdagPerEtkezesFajta>
    <Datum>2022-08-08</Datum>
    <EtkezesFajta>N</EtkezesFajta>
    <Adag>1989</Adag>
  </NapiAdagPerEtkezesFajta>
  <NapiAdagPerEtkezesFajta>
    <Datum>2022-08-08</Datum>
    <EtkezesFajta>D</EtkezesFajta>
    <Adag>18</Adag>
  </NapiAdagPerEtkezesFajta>
  <NapiAdagPerEtkezesFajta>
    <Datum>2022-08-09</Datum>
    <EtkezesFajta>N</EtkezesFajta>
    <Adag>1998</Adag>
  </NapiAdagPerEtkezesFajta>
  <NapiAdagPerEtkezesFajta>
    <Datum>2022-08-09</Datum>
    <EtkezesFajta>D</EtkezesFajta>
    <Adag>18</Adag>
  </NapiAdagPerEtkezesFajta>
  <NapiAdagPerEtkezesFajta>
    <Datum>2022-08-10</Datum>
    <EtkezesFajta>N</EtkezesFajta>
    <Adag>2012</Adag>
  </NapiAdagPerEtkezesFajta>
  <NapiAdagPerEtkezesFajta>
    <Datum>2022-08-10</Datum>
    <EtkezesFajta>D</EtkezesFajta>
    <Adag>18</Adag>
  </NapiAdagPerEtkezesFajta>
  <NapiAdagPerEtkezesFajta>
    <Datum>2022-08-11</Datum>
    <EtkezesFajta>N</EtkezesFajta>
    <Adag>2011</Adag>
  </NapiAdagPerEtkezesFajta>
  <NapiAdagPerEtkezesFajta>
    <Datum>2022-08-11</Datum>
    <EtkezesFajta>D</EtkezesFajta>
    <Adag>18</Adag>
  </NapiAdagPerEtkezesFajta>
  <NapiAdagPerEtkezesFajta>
    <Datum>2022-08-12</Datum>
    <EtkezesFajta>N</EtkezesFajta>
    <Adag>1998</Adag>
  </NapiAdagPerEtkezesFajta>
  <NapiAdagPerEtkezesFajta>
    <Datum>2022-08-12</Datum>
    <EtkezesFajta>D</EtkezesFajta>
    <Adag>18</Adag>
  </NapiAdagPerEtkezesFajta>
  <NapiAdagPerEtkezesFajta>
    <Datum>2022-08-15</Datum>
    <EtkezesFajta>N</EtkezesFajta>
    <Adag>2233</Adag>
  </NapiAdagPerEtkezesFajta>
  <NapiAdagPerEtkezesFajta>
    <Datum>2022-08-15</Datum>
    <EtkezesFajta>D</EtkezesFajta>
    <Adag>12</Adag>
  </NapiAdagPerEtkezesFajta>
  <NapiAdagPerEtkezesFajta>
    <Datum>2022-08-16</Datum>
    <EtkezesFajta>N</EtkezesFajta>
    <Adag>2237</Adag>
  </NapiAdagPerEtkezesFajta>
  <NapiAdagPerEtkezesFajta>
    <Datum>2022-08-16</Datum>
    <EtkezesFajta>D</EtkezesFajta>
    <Adag>12</Adag>
  </NapiAdagPerEtkezesFajta>
  <NapiAdagPerEtkezesFajta>
    <Datum>2022-08-17</Datum>
    <EtkezesFajta>D</EtkezesFajta>
    <Adag>12</Adag>
  </NapiAdagPerEtkezesFajta>
  <NapiAdagPerEtkezesFajta>
    <Datum>2022-08-17</Datum>
    <EtkezesFajta>N</EtkezesFajta>
    <Adag>2241</Adag>
  </NapiAdagPerEtkezesFajta>
  <NapiAdagPerEtkezesFajta>
    <Datum>2022-08-18</Datum>
    <EtkezesFajta>N</EtkezesFajta>
    <Adag>2218</Adag>
  </NapiAdagPerEtkezesFajta>
  <NapiAdagPerEtkezesFajta>
    <Datum>2022-08-18</Datum>
    <EtkezesFajta>D</EtkezesFajta>
    <Adag>12</Adag>
  </NapiAdagPerEtkezesFajta>
  <NapiAdagPerEtkezesFajta>
    <Datum>2022-08-19</Datum>
    <EtkezesFajta>N</EtkezesFajta>
    <Adag>2220</Adag>
  </NapiAdagPerEtkezesFajta>
  <NapiAdagPerEtkezesFajta>
    <Datum>2022-08-19</Datum>
    <EtkezesFajta>D</EtkezesFajta>
    <Adag>12</Adag>
  </NapiAdagPerEtkezesFajta>
  <NapiAdagPerEtkezesFajta>
    <Datum>2022-08-22</Datum>
    <EtkezesFajta>N</EtkezesFajta>
    <Adag>2755</Adag>
  </NapiAdagPerEtkezesFajta>
  <NapiAdagPerEtkezesFajta>
    <Datum>2022-08-22</Datum>
    <EtkezesFajta>D</EtkezesFajta>
    <Adag>5</Adag>
  </NapiAdagPerEtkezesFajta>
  <NapiAdagPerEtkezesFajta>
    <Datum>2022-08-23</Datum>
    <EtkezesFajta>N</EtkezesFajta>
    <Adag>2761</Adag>
  </NapiAdagPerEtkezesFajta>
  <NapiAdagPerEtkezesFajta>
    <Datum>2022-08-23</Datum>
    <EtkezesFajta>D</EtkezesFajta>
    <Adag>5</Adag>
  </NapiAdagPerEtkezesFajta>
  <NapiAdagPerEtkezesFajta>
    <Datum>2022-08-24</Datum>
    <EtkezesFajta>N</EtkezesFajta>
    <Adag>2764</Adag>
  </NapiAdagPerEtkezesFajta>
  <NapiAdagPerEtkezesFajta>
    <Datum>2022-08-24</Datum>
    <EtkezesFajta>D</EtkezesFajta>
    <Adag>5</Adag>
  </NapiAdagPerEtkezesFajta>
  <NapiAdagPerEtkezesFajta>
    <Datum>2022-08-25</Datum>
    <EtkezesFajta>N</EtkezesFajta>
    <Adag>2759</Adag>
  </NapiAdagPerEtkezesFajta>
  <NapiAdagPerEtkezesFajta>
    <Datum>2022-08-25</Datum>
    <EtkezesFajta>D</EtkezesFajta>
    <Adag>5</Adag>
  </NapiAdagPerEtkezesFajta>
  <NapiAdagPerEtkezesFajta>
    <Datum>2022-08-26</Datum>
    <EtkezesFajta>N</EtkezesFajta>
    <Adag>2590</Adag>
  </NapiAdagPerEtkezesFajta>
  <NapiAdagPerEtkezesFajta>
    <Datum>2022-08-26</Datum>
    <EtkezesFajta>D</EtkezesFajta>
    <Adag>5</Adag>
  </NapiAdagPerEtkezesFajta>
  <NapiAdagPerEtkezesFajta>
    <Datum>2022-08-29</Datum>
    <EtkezesFajta>N</EtkezesFajta>
    <Adag>1487</Adag>
  </NapiAdagPerEtkezesFajta>
  <NapiAdagPerEtkezesFajta>
    <Datum>2022-08-29</Datum>
    <EtkezesFajta>D</EtkezesFajta>
    <Adag>1</Adag>
  </NapiAdagPerEtkezesFajta>
  <NapiAdagPerEtkezesFajta>
    <Datum>2022-08-30</Datum>
    <EtkezesFajta>N</EtkezesFajta>
    <Adag>2786</Adag>
  </NapiAdagPerEtkezesFajta>
  <NapiAdagPerEtkezesFajta>
    <Datum>2022-08-30</Datum>
    <EtkezesFajta>D</EtkezesFajta>
    <Adag>7</Adag>
  </NapiAdagPerEtkezesFajta>
  <NapiAdagPerEtkezesFajta>
    <Datum>2022-08-31</Datum>
    <EtkezesFajta>N</EtkezesFajta>
    <Adag>2796</Adag>
  </NapiAdagPerEtkezesFajta>
  <NapiAdagPerEtkezesFajta>
    <Datum>2022-08-31</Datum>
    <EtkezesFajta>D</EtkezesFajta>
    <Adag>7</Adag>
  </NapiAdagPerEtkezesFajta>
  <NapiAdagPerEtkezesFajta>
    <Datum>2022-09-01</Datum>
    <EtkezesFajta>N</EtkezesFajta>
    <Adag>14385</Adag>
  </NapiAdagPerEtkezesFajta>
  <NapiAdagPerEtkezesFajta>
    <Datum>2022-09-01</Datum>
    <EtkezesFajta>D</EtkezesFajta>
    <Adag>117</Adag>
  </NapiAdagPerEtkezesFajta>
  <NapiAdagPerEtkezesFajta>
    <Datum>2022-09-02</Datum>
    <EtkezesFajta>N</EtkezesFajta>
    <Adag>13323</Adag>
  </NapiAdagPerEtkezesFajta>
  <NapiAdagPerEtkezesFajta>
    <Datum>2022-09-02</Datum>
    <EtkezesFajta>D</EtkezesFajta>
    <Adag>101</Adag>
  </NapiAdagPerEtkezesFajta>
  <NapiAdagPerEtkezesFajta>
    <Datum>2022-09-03</Datum>
    <EtkezesFajta>N</EtkezesFajta>
    <Adag>9</Adag>
  </NapiAdagPerEtkezesFajta>
  <NapiAdagPerEtkezesFajta>
    <Datum>2022-09-04</Datum>
    <EtkezesFajta>N</EtkezesFajta>
    <Adag>9</Adag>
  </NapiAdagPerEtkezesFajta>
  <NapiAdagPerEtkezesFajta>
    <Datum>2022-09-05</Datum>
    <EtkezesFajta>N</EtkezesFajta>
    <Adag>13175</Adag>
  </NapiAdagPerEtkezesFajta>
  <NapiAdagPerEtkezesFajta>
    <Datum>2022-09-05</Datum>
    <EtkezesFajta>D</EtkezesFajta>
    <Adag>134</Adag>
  </NapiAdagPerEtkezesFajta>
  <NapiAdagPerEtkezesFajta>
    <Datum>2022-09-06</Datum>
    <EtkezesFajta>D</EtkezesFajta>
    <Adag>133</Adag>
  </NapiAdagPerEtkezesFajta>
  <NapiAdagPerEtkezesFajta>
    <Datum>2022-09-06</Datum>
    <EtkezesFajta>N</EtkezesFajta>
    <Adag>13195</Adag>
  </NapiAdagPerEtkezesFajta>
  <NapiAdagPerEtkezesFajta>
    <Datum>2022-09-07</Datum>
    <EtkezesFajta>D</EtkezesFajta>
    <Adag>134</Adag>
  </NapiAdagPerEtkezesFajta>
  <NapiAdagPerEtkezesFajta>
    <Datum>2022-09-07</Datum>
    <EtkezesFajta>N</EtkezesFajta>
    <Adag>13205</Adag>
  </NapiAdagPerEtkezesFajta>
  <NapiAdagPerEtkezesFajta>
    <Datum>2022-09-08</Datum>
    <EtkezesFajta>N</EtkezesFajta>
    <Adag>13198</Adag>
  </NapiAdagPerEtkezesFajta>
  <NapiAdagPerEtkezesFajta>
    <Datum>2022-09-08</Datum>
    <EtkezesFajta>D</EtkezesFajta>
    <Adag>133</Adag>
  </NapiAdagPerEtkezesFajta>
  <NapiAdagPerEtkezesFajta>
    <Datum>2022-09-09</Datum>
    <EtkezesFajta>N</EtkezesFajta>
    <Adag>12129</Adag>
  </NapiAdagPerEtkezesFajta>
  <NapiAdagPerEtkezesFajta>
    <Datum>2022-09-09</Datum>
    <EtkezesFajta>D</EtkezesFajta>
    <Adag>111</Adag>
  </NapiAdagPerEtkezesFajta>
  <NapiAdagPerEtkezesFajta>
    <Datum>2022-09-12</Datum>
    <EtkezesFajta>N</EtkezesFajta>
    <Adag>14148</Adag>
  </NapiAdagPerEtkezesFajta>
  <NapiAdagPerEtkezesFajta>
    <Datum>2022-09-12</Datum>
    <EtkezesFajta>D</EtkezesFajta>
    <Adag>132</Adag>
  </NapiAdagPerEtkezesFajta>
  <NapiAdagPerEtkezesFajta>
    <Datum>2022-09-13</Datum>
    <EtkezesFajta>N</EtkezesFajta>
    <Adag>14192</Adag>
  </NapiAdagPerEtkezesFajta>
  <NapiAdagPerEtkezesFajta>
    <Datum>2022-09-13</Datum>
    <EtkezesFajta>D</EtkezesFajta>
    <Adag>134</Adag>
  </NapiAdagPerEtkezesFajta>
  <NapiAdagPerEtkezesFajta>
    <Datum>2022-09-14</Datum>
    <EtkezesFajta>D</EtkezesFajta>
    <Adag>134</Adag>
  </NapiAdagPerEtkezesFajta>
  <NapiAdagPerEtkezesFajta>
    <Datum>2022-09-14</Datum>
    <EtkezesFajta>N</EtkezesFajta>
    <Adag>14199</Adag>
  </NapiAdagPerEtkezesFajta>
  <NapiAdagPerEtkezesFajta>
    <Datum>2022-09-15</Datum>
    <EtkezesFajta>D</EtkezesFajta>
    <Adag>133</Adag>
  </NapiAdagPerEtkezesFajta>
  <NapiAdagPerEtkezesFajta>
    <Datum>2022-09-15</Datum>
    <EtkezesFajta>N</EtkezesFajta>
    <Adag>14186</Adag>
  </NapiAdagPerEtkezesFajta>
  <NapiAdagPerEtkezesFajta>
    <Datum>2022-09-16</Datum>
    <EtkezesFajta>N</EtkezesFajta>
    <Adag>13027</Adag>
  </NapiAdagPerEtkezesFajta>
  <NapiAdagPerEtkezesFajta>
    <Datum>2022-09-16</Datum>
    <EtkezesFajta>D</EtkezesFajta>
    <Adag>108</Adag>
  </NapiAdagPerEtkezesFajta>
  <NapiAdagPerEtkezesFajta>
    <Datum>2022-09-19</Datum>
    <EtkezesFajta>N</EtkezesFajta>
    <Adag>11566</Adag>
  </NapiAdagPerEtkezesFajta>
  <NapiAdagPerEtkezesFajta>
    <Datum>2022-09-19</Datum>
    <EtkezesFajta>D</EtkezesFajta>
    <Adag>97</Adag>
  </NapiAdagPerEtkezesFajta>
  <NapiAdagPerEtkezesFajta>
    <Datum>2022-09-20</Datum>
    <EtkezesFajta>N</EtkezesFajta>
    <Adag>11593</Adag>
  </NapiAdagPerEtkezesFajta>
  <NapiAdagPerEtkezesFajta>
    <Datum>2022-09-20</Datum>
    <EtkezesFajta>D</EtkezesFajta>
    <Adag>97</Adag>
  </NapiAdagPerEtkezesFajta>
  <NapiAdagPerEtkezesFajta>
    <Datum>2022-09-21</Datum>
    <EtkezesFajta>N</EtkezesFajta>
    <Adag>11612</Adag>
  </NapiAdagPerEtkezesFajta>
  <NapiAdagPerEtkezesFajta>
    <Datum>2022-09-21</Datum>
    <EtkezesFajta>D</EtkezesFajta>
    <Adag>97</Adag>
  </NapiAdagPerEtkezesFajta>
  <NapiAdagPerEtkezesFajta>
    <Datum>2022-09-22</Datum>
    <EtkezesFajta>D</EtkezesFajta>
    <Adag>96</Adag>
  </NapiAdagPerEtkezesFajta>
  <NapiAdagPerEtkezesFajta>
    <Datum>2022-09-22</Datum>
    <EtkezesFajta>N</EtkezesFajta>
    <Adag>11609</Adag>
  </NapiAdagPerEtkezesFajta>
  <NapiAdagPerEtkezesFajta>
    <Datum>2022-09-23</Datum>
    <EtkezesFajta>D</EtkezesFajta>
    <Adag>83</Adag>
  </NapiAdagPerEtkezesFajta>
  <NapiAdagPerEtkezesFajta>
    <Datum>2022-09-23</Datum>
    <EtkezesFajta>N</EtkezesFajta>
    <Adag>11085</Adag>
  </NapiAdagPerEtkezesFajta>
  <NapiAdagPerEtkezesFajta>
    <Datum>2022-09-26</Datum>
    <EtkezesFajta>N</EtkezesFajta>
    <Adag>13064</Adag>
  </NapiAdagPerEtkezesFajta>
  <NapiAdagPerEtkezesFajta>
    <Datum>2022-09-26</Datum>
    <EtkezesFajta>D</EtkezesFajta>
    <Adag>109</Adag>
  </NapiAdagPerEtkezesFajta>
  <NapiAdagPerEtkezesFajta>
    <Datum>2022-09-27</Datum>
    <EtkezesFajta>D</EtkezesFajta>
    <Adag>109</Adag>
  </NapiAdagPerEtkezesFajta>
  <NapiAdagPerEtkezesFajta>
    <Datum>2022-09-27</Datum>
    <EtkezesFajta>N</EtkezesFajta>
    <Adag>13109</Adag>
  </NapiAdagPerEtkezesFajta>
  <NapiAdagPerEtkezesFajta>
    <Datum>2022-09-28</Datum>
    <EtkezesFajta>D</EtkezesFajta>
    <Adag>109</Adag>
  </NapiAdagPerEtkezesFajta>
  <NapiAdagPerEtkezesFajta>
    <Datum>2022-09-28</Datum>
    <EtkezesFajta>N</EtkezesFajta>
    <Adag>13122</Adag>
  </NapiAdagPerEtkezesFajta>
  <NapiAdagPerEtkezesFajta>
    <Datum>2022-09-29</Datum>
    <EtkezesFajta>N</EtkezesFajta>
    <Adag>13431</Adag>
  </NapiAdagPerEtkezesFajta>
  <NapiAdagPerEtkezesFajta>
    <Datum>2022-09-29</Datum>
    <EtkezesFajta>D</EtkezesFajta>
    <Adag>109</Adag>
  </NapiAdagPerEtkezesFajta>
  <NapiAdagPerEtkezesFajta>
    <Datum>2022-09-30</Datum>
    <EtkezesFajta>D</EtkezesFajta>
    <Adag>93</Adag>
  </NapiAdagPerEtkezesFajta>
  <NapiAdagPerEtkezesFajta>
    <Datum>2022-09-30</Datum>
    <EtkezesFajta>N</EtkezesFajta>
    <Adag>12500</Adag>
  </NapiAdagPerEtkezesFajta>
  <NapiAdagPerEtkezesFajta>
    <Datum>2022-10-03</Datum>
    <EtkezesFajta>N</EtkezesFajta>
    <Adag>12109</Adag>
  </NapiAdagPerEtkezesFajta>
  <NapiAdagPerEtkezesFajta>
    <Datum>2022-10-03</Datum>
    <EtkezesFajta>D</EtkezesFajta>
    <Adag>120</Adag>
  </NapiAdagPerEtkezesFajta>
  <NapiAdagPerEtkezesFajta>
    <Datum>2022-10-04</Datum>
    <EtkezesFajta>N</EtkezesFajta>
    <Adag>12830</Adag>
  </NapiAdagPerEtkezesFajta>
  <NapiAdagPerEtkezesFajta>
    <Datum>2022-10-04</Datum>
    <EtkezesFajta>D</EtkezesFajta>
    <Adag>123</Adag>
  </NapiAdagPerEtkezesFajta>
  <NapiAdagPerEtkezesFajta>
    <Datum>2022-10-05</Datum>
    <EtkezesFajta>N</EtkezesFajta>
    <Adag>12832</Adag>
  </NapiAdagPerEtkezesFajta>
  <NapiAdagPerEtkezesFajta>
    <Datum>2022-10-05</Datum>
    <EtkezesFajta>D</EtkezesFajta>
    <Adag>124</Adag>
  </NapiAdagPerEtkezesFajta>
  <NapiAdagPerEtkezesFajta>
    <Datum>2022-10-06</Datum>
    <EtkezesFajta>D</EtkezesFajta>
    <Adag>114</Adag>
  </NapiAdagPerEtkezesFajta>
  <NapiAdagPerEtkezesFajta>
    <Datum>2022-10-06</Datum>
    <EtkezesFajta>N</EtkezesFajta>
    <Adag>12199</Adag>
  </NapiAdagPerEtkezesFajta>
  <NapiAdagPerEtkezesFajta>
    <Datum>2022-10-07</Datum>
    <EtkezesFajta>N</EtkezesFajta>
    <Adag>11307</Adag>
  </NapiAdagPerEtkezesFajta>
  <NapiAdagPerEtkezesFajta>
    <Datum>2022-10-07</Datum>
    <EtkezesFajta>D</EtkezesFajta>
    <Adag>91</Adag>
  </NapiAdagPerEtkezesFajta>
  <NapiAdagPerEtkezesFajta>
    <Datum>2022-10-10</Datum>
    <EtkezesFajta>D</EtkezesFajta>
    <Adag>128</Adag>
  </NapiAdagPerEtkezesFajta>
  <NapiAdagPerEtkezesFajta>
    <Datum>2022-10-10</Datum>
    <EtkezesFajta>N</EtkezesFajta>
    <Adag>12870</Adag>
  </NapiAdagPerEtkezesFajta>
  <NapiAdagPerEtkezesFajta>
    <Datum>2022-10-11</Datum>
    <EtkezesFajta>N</EtkezesFajta>
    <Adag>13012</Adag>
  </NapiAdagPerEtkezesFajta>
  <NapiAdagPerEtkezesFajta>
    <Datum>2022-10-11</Datum>
    <EtkezesFajta>D</EtkezesFajta>
    <Adag>130</Adag>
  </NapiAdagPerEtkezesFajta>
  <NapiAdagPerEtkezesFajta>
    <Datum>2022-10-12</Datum>
    <EtkezesFajta>D</EtkezesFajta>
    <Adag>131</Adag>
  </NapiAdagPerEtkezesFajta>
  <NapiAdagPerEtkezesFajta>
    <Datum>2022-10-12</Datum>
    <EtkezesFajta>N</EtkezesFajta>
    <Adag>13010</Adag>
  </NapiAdagPerEtkezesFajta>
  <NapiAdagPerEtkezesFajta>
    <Datum>2022-10-13</Datum>
    <EtkezesFajta>N</EtkezesFajta>
    <Adag>13001</Adag>
  </NapiAdagPerEtkezesFajta>
  <NapiAdagPerEtkezesFajta>
    <Datum>2022-10-13</Datum>
    <EtkezesFajta>D</EtkezesFajta>
    <Adag>128</Adag>
  </NapiAdagPerEtkezesFajta>
  <NapiAdagPerEtkezesFajta>
    <Datum>2022-10-14</Datum>
    <EtkezesFajta>D</EtkezesFajta>
    <Adag>105</Adag>
  </NapiAdagPerEtkezesFajta>
  <NapiAdagPerEtkezesFajta>
    <Datum>2022-10-14</Datum>
    <EtkezesFajta>N</EtkezesFajta>
    <Adag>11789</Adag>
  </NapiAdagPerEtkezesFajta>
  <NapiAdagPerEtkezesFajta>
    <Datum>2022-10-15</Datum>
    <EtkezesFajta>N</EtkezesFajta>
    <Adag>5757</Adag>
  </NapiAdagPerEtkezesFajta>
  <NapiAdagPerEtkezesFajta>
    <Datum>2022-10-15</Datum>
    <EtkezesFajta>D</EtkezesFajta>
    <Adag>63</Adag>
  </NapiAdagPerEtkezesFajta>
  <NapiAdagPerEtkezesFajta>
    <Datum>2022-10-17</Datum>
    <EtkezesFajta>N</EtkezesFajta>
    <Adag>12276</Adag>
  </NapiAdagPerEtkezesFajta>
  <NapiAdagPerEtkezesFajta>
    <Datum>2022-10-17</Datum>
    <EtkezesFajta>D</EtkezesFajta>
    <Adag>119</Adag>
  </NapiAdagPerEtkezesFajta>
  <NapiAdagPerEtkezesFajta>
    <Datum>2022-10-18</Datum>
    <EtkezesFajta>N</EtkezesFajta>
    <Adag>12485</Adag>
  </NapiAdagPerEtkezesFajta>
  <NapiAdagPerEtkezesFajta>
    <Datum>2022-10-18</Datum>
    <EtkezesFajta>D</EtkezesFajta>
    <Adag>121</Adag>
  </NapiAdagPerEtkezesFajta>
  <NapiAdagPerEtkezesFajta>
    <Datum>2022-10-19</Datum>
    <EtkezesFajta>N</EtkezesFajta>
    <Adag>12497</Adag>
  </NapiAdagPerEtkezesFajta>
  <NapiAdagPerEtkezesFajta>
    <Datum>2022-10-19</Datum>
    <EtkezesFajta>D</EtkezesFajta>
    <Adag>122</Adag>
  </NapiAdagPerEtkezesFajta>
  <NapiAdagPerEtkezesFajta>
    <Datum>2022-10-20</Datum>
    <EtkezesFajta>D</EtkezesFajta>
    <Adag>116</Adag>
  </NapiAdagPerEtkezesFajta>
  <NapiAdagPerEtkezesFajta>
    <Datum>2022-10-20</Datum>
    <EtkezesFajta>N</EtkezesFajta>
    <Adag>12311</Adag>
  </NapiAdagPerEtkezesFajta>
  <NapiAdagPerEtkezesFajta>
    <Datum>2022-10-21</Datum>
    <EtkezesFajta>N</EtkezesFajta>
    <Adag>11330</Adag>
  </NapiAdagPerEtkezesFajta>
  <NapiAdagPerEtkezesFajta>
    <Datum>2022-10-21</Datum>
    <EtkezesFajta>D</EtkezesFajta>
    <Adag>97</Adag>
  </NapiAdagPerEtkezesFajta>
  <NapiAdagPerEtkezesFajta>
    <Datum>2022-10-24</Datum>
    <EtkezesFajta>N</EtkezesFajta>
    <Adag>13668</Adag>
  </NapiAdagPerEtkezesFajta>
  <NapiAdagPerEtkezesFajta>
    <Datum>2022-10-24</Datum>
    <EtkezesFajta>D</EtkezesFajta>
    <Adag>129</Adag>
  </NapiAdagPerEtkezesFajta>
  <NapiAdagPerEtkezesFajta>
    <Datum>2022-10-25</Datum>
    <EtkezesFajta>N</EtkezesFajta>
    <Adag>13722</Adag>
  </NapiAdagPerEtkezesFajta>
  <NapiAdagPerEtkezesFajta>
    <Datum>2022-10-25</Datum>
    <EtkezesFajta>D</EtkezesFajta>
    <Adag>132</Adag>
  </NapiAdagPerEtkezesFajta>
  <NapiAdagPerEtkezesFajta>
    <Datum>2022-10-26</Datum>
    <EtkezesFajta>D</EtkezesFajta>
    <Adag>132</Adag>
  </NapiAdagPerEtkezesFajta>
  <NapiAdagPerEtkezesFajta>
    <Datum>2022-10-26</Datum>
    <EtkezesFajta>N</EtkezesFajta>
    <Adag>13699</Adag>
  </NapiAdagPerEtkezesFajta>
  <NapiAdagPerEtkezesFajta>
    <Datum>2022-10-27</Datum>
    <EtkezesFajta>D</EtkezesFajta>
    <Adag>129</Adag>
  </NapiAdagPerEtkezesFajta>
  <NapiAdagPerEtkezesFajta>
    <Datum>2022-10-27</Datum>
    <EtkezesFajta>N</EtkezesFajta>
    <Adag>13730</Adag>
  </NapiAdagPerEtkezesFajta>
  <NapiAdagPerEtkezesFajta>
    <Datum>2022-10-28</Datum>
    <EtkezesFajta>D</EtkezesFajta>
    <Adag>95</Adag>
  </NapiAdagPerEtkezesFajta>
  <NapiAdagPerEtkezesFajta>
    <Datum>2022-10-28</Datum>
    <EtkezesFajta>N</EtkezesFajta>
    <Adag>11550</Adag>
  </NapiAdagPerEtkezesFajta>
  <NapiAdagPerEtkezesFajta>
    <Datum>2022-11-02</Datum>
    <EtkezesFajta>N</EtkezesFajta>
    <Adag>12145</Adag>
  </NapiAdagPerEtkezesFajta>
  <NapiAdagPerEtkezesFajta>
    <Datum>2022-11-02</Datum>
    <EtkezesFajta>D</EtkezesFajta>
    <Adag>116</Adag>
  </NapiAdagPerEtkezesFajta>
  <NapiAdagPerEtkezesFajta>
    <Datum>2022-11-03</Datum>
    <EtkezesFajta>N</EtkezesFajta>
    <Adag>12382</Adag>
  </NapiAdagPerEtkezesFajta>
  <NapiAdagPerEtkezesFajta>
    <Datum>2022-11-03</Datum>
    <EtkezesFajta>D</EtkezesFajta>
    <Adag>116</Adag>
  </NapiAdagPerEtkezesFajta>
  <NapiAdagPerEtkezesFajta>
    <Datum>2022-11-04</Datum>
    <EtkezesFajta>D</EtkezesFajta>
    <Adag>103</Adag>
  </NapiAdagPerEtkezesFajta>
  <NapiAdagPerEtkezesFajta>
    <Datum>2022-11-04</Datum>
    <EtkezesFajta>N</EtkezesFajta>
    <Adag>11603</Adag>
  </NapiAdagPerEtkezesFajta>
  <NapiAdagPerEtkezesFajta>
    <Datum>2022-11-07</Datum>
    <EtkezesFajta>D</EtkezesFajta>
    <Adag>81</Adag>
  </NapiAdagPerEtkezesFajta>
  <NapiAdagPerEtkezesFajta>
    <Datum>2022-11-07</Datum>
    <EtkezesFajta>N</EtkezesFajta>
    <Adag>9471</Adag>
  </NapiAdagPerEtkezesFajta>
  <NapiAdagPerEtkezesFajta>
    <Datum>2022-11-08</Datum>
    <EtkezesFajta>N</EtkezesFajta>
    <Adag>9480</Adag>
  </NapiAdagPerEtkezesFajta>
  <NapiAdagPerEtkezesFajta>
    <Datum>2022-11-08</Datum>
    <EtkezesFajta>D</EtkezesFajta>
    <Adag>83</Adag>
  </NapiAdagPerEtkezesFajta>
  <NapiAdagPerEtkezesFajta>
    <Datum>2022-11-09</Datum>
    <EtkezesFajta>N</EtkezesFajta>
    <Adag>9442</Adag>
  </NapiAdagPerEtkezesFajta>
  <NapiAdagPerEtkezesFajta>
    <Datum>2022-11-09</Datum>
    <EtkezesFajta>D</EtkezesFajta>
    <Adag>84</Adag>
  </NapiAdagPerEtkezesFajta>
  <NapiAdagPerEtkezesFajta>
    <Datum>2022-11-10</Datum>
    <EtkezesFajta>D</EtkezesFajta>
    <Adag>81</Adag>
  </NapiAdagPerEtkezesFajta>
  <NapiAdagPerEtkezesFajta>
    <Datum>2022-11-10</Datum>
    <EtkezesFajta>N</EtkezesFajta>
    <Adag>9159</Adag>
  </NapiAdagPerEtkezesFajta>
  <NapiAdagPerEtkezesFajta>
    <Datum>2022-11-11</Datum>
    <EtkezesFajta>D</EtkezesFajta>
    <Adag>61</Adag>
  </NapiAdagPerEtkezesFajta>
  <NapiAdagPerEtkezesFajta>
    <Datum>2022-11-11</Datum>
    <EtkezesFajta>N</EtkezesFajta>
    <Adag>8476</Adag>
  </NapiAdagPerEtkezesFajta>
  <NapiAdagPerEtkezesFajta>
    <Datum>2022-11-14</Datum>
    <EtkezesFajta>D</EtkezesFajta>
    <Adag>97</Adag>
  </NapiAdagPerEtkezesFajta>
  <NapiAdagPerEtkezesFajta>
    <Datum>2022-11-14</Datum>
    <EtkezesFajta>N</EtkezesFajta>
    <Adag>10731</Adag>
  </NapiAdagPerEtkezesFajta>
  <NapiAdagPerEtkezesFajta>
    <Datum>2022-11-15</Datum>
    <EtkezesFajta>D</EtkezesFajta>
    <Adag>99</Adag>
  </NapiAdagPerEtkezesFajta>
  <NapiAdagPerEtkezesFajta>
    <Datum>2022-11-15</Datum>
    <EtkezesFajta>N</EtkezesFajta>
    <Adag>10776</Adag>
  </NapiAdagPerEtkezesFajta>
  <NapiAdagPerEtkezesFajta>
    <Datum>2022-11-16</Datum>
    <EtkezesFajta>D</EtkezesFajta>
    <Adag>99</Adag>
  </NapiAdagPerEtkezesFajta>
  <NapiAdagPerEtkezesFajta>
    <Datum>2022-11-16</Datum>
    <EtkezesFajta>N</EtkezesFajta>
    <Adag>10782</Adag>
  </NapiAdagPerEtkezesFajta>
  <NapiAdagPerEtkezesFajta>
    <Datum>2022-11-17</Datum>
    <EtkezesFajta>D</EtkezesFajta>
    <Adag>96</Adag>
  </NapiAdagPerEtkezesFajta>
  <NapiAdagPerEtkezesFajta>
    <Datum>2022-11-17</Datum>
    <EtkezesFajta>N</EtkezesFajta>
    <Adag>10789</Adag>
  </NapiAdagPerEtkezesFajta>
  <NapiAdagPerEtkezesFajta>
    <Datum>2022-11-18</Datum>
    <EtkezesFajta>D</EtkezesFajta>
    <Adag>80</Adag>
  </NapiAdagPerEtkezesFajta>
  <NapiAdagPerEtkezesFajta>
    <Datum>2022-11-18</Datum>
    <EtkezesFajta>N</EtkezesFajta>
    <Adag>9875</Adag>
  </NapiAdagPerEtkezesFajta>
</ArrayOfNapiAdagPerEtkezesFajta>